mdgenerator/__init__.py
mdgenerator/cli.py
mdgenerator/mdgenerator.py
mdgenerator-0.1.0.dist-info/LICENSE
mdgenerator-0.1.0.dist-info/METADATA
mdgenerator-0.1.0.dist-info/WHEEL
mdgenerator-0.1.0.dist-info/entry_points.txt
mdgenerator-0.1.0.dist-info/top_level.txt
mdgenerator-0.1.0.dist-info/RECORD
