Metadata-Version: 2.1
Name: mdgenerator
Version: 0.1.0
Summary: Package to generate different kind of markdown texts
Home-page: https://github.com/nilansaha/mdgenerator
Author: Nilan Saha
License: Apache 2.0
Platform: UNKNOWN
Classifier: Programming Language :: Python
Requires-Python: >=3.6
Requires-Dist: numpy (==1.16.2)
Requires-Dist: pandas (==0.24.2)
